Metadata-Version: 1.1
Name: django-testproject
Version: 0.1.2
Summary: Universal project for running unit tests of Django applications
Home-page: https://git.linaro.org/lava/django-testproject.git
Author: Linaro Limited
Author-email: lava-team@linaro.org
License: LGPLv3
Keywords: django,testing
Platform: UNKNOWN
Classifier: Development Status :: 4 - Beta
Classifier: Environment :: Web Environment
Classifier: Framework :: Django
Classifier: Intended Audience :: Developers
Classifier: License :: OSI Approved :: GNU Library or Lesser General Public License (LGPL)
Classifier: Operating System :: OS Independent
Classifier: Programming Language :: Python :: 2.6
Classifier: Programming Language :: Python :: 2.7
Classifier: Topic :: Software Development :: Testing
